gistsync/__init__.py
gistsync/__main__.py
gistsync/consts.py
gistsync/entry_points_console_scripts.py
gistsync/gist_dir.py
gistsync/gist_ops.py
gistsync/global_settings.py
gistsync/main.py
gistsync/utils.py
gistsync-0.5.0.dist-info/LICENSE
gistsync-0.5.0.dist-info/METADATA
gistsync-0.5.0.dist-info/WHEEL
gistsync-0.5.0.dist-info/entry_points.txt
gistsync-0.5.0.dist-info/top_level.txt
gistsync-0.5.0.dist-info/RECORD
