Metadata-Version: 2.1
Name: gistsync
Version: 0.5.0
Summary: UNKNOWN
Home-page: https://github.com/Cologler/gist-sync-python
Author: Cologler
Author-email: skyoflw@gmail.com
License: MIT License
Platform: UNKNOWN
Classifier: License :: OSI Approved :: MIT License
Classifier: Programming Language :: Python :: 3.7
Classifier: Programming Language :: Python :: 3.8
Requires-Dist: anyioc
Requires-Dist: click-anno
Requires-Dist: colorama
Requires-Dist: fsoopify
Requires-Dist: pygithub
Requires-Dist: requests
